[{"r":"86","t":"05:48:52","h":"Ouest","s":"25N-H54N000I-80-I"},{"r":"86","t":"05:48:52","h":"Ouest","s":"25N-H54N100F-80-F1"},{"r":"86","t":"05:48:52","h":"Ouest","s":"25N-H54N200F-80-F2"},{"r":"86","t":"05:48:52","h":"Ouest","s":"25N-H54N300F-80-F3"},{"r":"86","t":"05:48:52","h":"Ouest","s":"25N-H54N400F-80-F4"},{"r":"86","t":"05:48:52","h":"Ouest","s":"25N-H54NV10I-80-I"},{"r":"86","t":"05:48:52","h":"Ouest","s":"25N-H54NV20I-80-I"},{"r":"86","t":"05:48:52","h":"Ouest","s":"25S-H54S000I-82-I"},{"r":"86","t":"05:48:52","h":"Ouest","s":"25S-H54S100F-80-F1"},{"r":"86","t":"05:48:52","h":"Ouest","s":"25S-H54S200F-80-F2"},{"r":"86","t":"05:52:52","h":"Ouest","s":"25N-H54N000A-80-A"},{"r":"86","t":"05:52:52","h":"Ouest","s":"25N-H54NV10A-80-A"},{"r":"86","t":"05:52:52","h":"Ouest","s":"25N-H54NV20A-80-A"},{"r":"86","t":"05:52:52","h":"Ouest","s":"25S-H54S000A-83-A"},{"r":"86","t":"06:00:52","h":"Ouest","s":"25N-H54N000S-80-S"},{"r":"86","t":"06:00:52","h":"Ouest","s":"25N-H54NV10S-82-S"},{"r":"86","t":"06:00:52","h":"Ouest","s":"25N-H54NV20S-80-S"},{"r":"86","t":"06:00:52","h":"Ouest","s":"25S-H54S000S-82-S"},{"r":"86","t":"06:17:52","h":"Ouest","s":"25N-H54N000I-80-I"},{"r":"86","t":"06:17:52","h":"Ouest","s":"25N-H54N100F-80-F1"},{"r":"86","t":"06:17:52","h":"Ouest","s":"25N-H54N200F-80-F2"},{"r":"86","t":"06:17:52","h":"Ouest","s":"25N-H54N300F-80-F3"},{"r":"86","t":"06:17:52","h":"Ouest","s":"25N-H54N400F-80-F4"},{"r":"86","t":"06:17:52","h":"Ouest","s":"25N-H54NV10I-80-I"},{"r":"86","t":"06:17:52","h":"Ouest","s":"25N-H54NV20I-80-I"},{"r":"86","t":"06:17:52","h":"Ouest","s":"25S-H54S000I-82-I"},{"r":"86","t":"06:17:52","h":"Ouest","s":"25S-H54S100F-80-F1"},{"r":"86","t":"06:17:52","h":"Ouest","s":"25S-H54S200F-80-F2"},{"r":"86","t":"06:25:52","h":"Ouest","s":"25N-H54N000A-80-A"},{"r":"86","t":"06:25:52","h":"Ouest","s":"25N-H54NV10A-80-A"},{"r":"86","t":"06:25:52","h":"Ouest","s":"25N-H54NV20A-80-A"},{"r":"86","t":"06:25:52","h":"Ouest","s":"25S-H54S000A-83-A"},{"r":"86","t":"06:29:52","h":"Ouest","s":"25N-H54N000S-80-S"},{"r":"86","t":"06:29:52","h":"Ouest","s":"25N-H54NV10S-82-S"},{"r":"86","t":"06:29:52","h":"Ouest","s":"25N-H54NV20S-80-S"},{"r":"86","t":"06:29:52","h":"Ouest","s":"25S-H54S000S-82-S"},{"r":"86","t":"06:51:52","h":"Ouest","s":"25N-H54N000I-80-I"},{"r":"86","t":"06:51:52","h":"Ouest","s":"25N-H54N100F-80-F1"},{"r":"86","t":"06:51:52","h":"Ouest","s":"25N-H54N200F-80-F2"},{"r":"86","t":"06:51:52","h":"Ouest","s":"25N-H54N300F-80-F3"},{"r":"86","t":"06:51:52","h":"Ouest","s":"25N-H54N400F-80-F4"},{"r":"86","t":"06:51:52","h":"Ouest","s":"25N-H54NV10I-80-I"},{"r":"86","t":"06:51:52","h":"Ouest","s":"25N-H54NV20I-80-I"},{"r":"86","t":"06:51:52","h":"Ouest","s":"25S-H54S000I-82-I"},{"r":"86","t":"06:51:52","h":"Ouest","s":"25S-H54S100F-80-F1"},{"r":"86","t":"06:51:52","h":"Ouest","s":"25S-H54S200F-80-F2"},{"r":"86","t":"07:00:52","h":"Ouest","s":"25N-H54N000S-80-S"},{"r":"86","t":"07:00:52","h":"Ouest","s":"25N-H54NV10S-82-S"},{"r":"86","t":"07:00:52","h":"Ouest","s":"25N-H54NV20S-80-S"},{"r":"86","t":"07:00:52","h":"Ouest","s":"25S-H54S000S-82-S"},{"r":"86","t":"07:02:52","h":"Ouest","s":"25N-H54N000A-80-A"},{"r":"86","t":"07:02:52","h":"Ouest","s":"25N-H54NV10A-80-A"},{"r":"86","t":"07:02:52","h":"Ouest","s":"25N-H54NV20A-80-A"},{"r":"86","t":"07:02:52","h":"Ouest","s":"25S-H54S000A-83-A"},{"r":"86","t":"07:25:52","h":"Ouest","s":"25N-H54N000I-80-I"},{"r":"86","t":"07:25:52","h":"Ouest","s":"25N-H54N100F-80-F1"},{"r":"86","t":"07:25:52","h":"Ouest","s":"25N-H54N200F-80-F2"},{"r":"86","t":"07:25:52","h":"Ouest","s":"25N-H54N300F-80-F3"},{"r":"86","t":"07:25:52","h":"Ouest","s":"25N-H54N400F-80-F4"},{"r":"86","t":"07:25:52","h":"Ouest","s":"25N-H54NV10I-80-I"},{"r":"86","t":"07:25:52","h":"Ouest","s":"25N-H54NV20I-80-I"},{"r":"86","t":"07:25:52","h":"Ouest","s":"25S-H54S000I-82-I"},{"r":"86","t":"07:25:52","h":"Ouest","s":"25S-H54S100F-80-F1"},{"r":"86","t":"07:25:52","h":"Ouest","s":"25S-H54S200F-80-F2"},{"r":"86","t":"07:34:52","h":"Ouest","s":"25N-H54N000S-80-S"},{"r":"86","t":"07:34:52","h":"Ouest","s":"25N-H54NV10S-82-S"},{"r":"86","t":"07:34:52","h":"Ouest","s":"25N-H54NV20S-80-S"},{"r":"86","t":"07:34:52","h":"Ouest","s":"25S-H54S000S-82-S"},{"r":"86","t":"07:35:52","h":"Ouest","s":"25N-H54N000A-80-A"},{"r":"86","t":"07:35:52","h":"Ouest","s":"25N-H54NV10A-80-A"},{"r":"86","t":"07:35:52","h":"Ouest","s":"25N-H54NV20A-80-A"},{"r":"86","t":"07:35:52","h":"Ouest","s":"25S-H54S000A-83-A"},{"r":"86","t":"08:01:52","h":"Ouest","s":"25N-H54N000I-80-I"},{"r":"86","t":"08:01:52","h":"Ouest","s":"25N-H54N100F-80-F1"},{"r":"86","t":"08:01:52","h":"Ouest","s":"25N-H54N200F-80-F2"},{"r":"86","t":"08:01:52","h":"Ouest","s":"25N-H54N300F-80-F3"},{"r":"86","t":"08:01:52","h":"Ouest","s":"25N-H54N400F-80-F4"},{"r":"86","t":"08:01:52","h":"Ouest","s":"25N-H54NV10I-80-I"},{"r":"86","t":"08:01:52","h":"Ouest","s":"25N-H54NV20I-80-I"},{"r":"86","t":"08:01:52","h":"Ouest","s":"25S-H54S000I-82-I"},{"r":"86","t":"08:01:52","h":"Ouest","s":"25S-H54S100F-80-F1"},{"r":"86","t":"08:01:52","h":"Ouest","s":"25S-H54S200F-80-F2"},{"r":"86","t":"08:07:31","h":"Ouest","s":"25N-H54N000S-80-S"},{"r":"86","t":"08:07:31","h":"Ouest","s":"25N-H54NV10S-82-S"},{"r":"86","t":"08:07:31","h":"Ouest","s":"25N-H54NV20S-80-S"},{"r":"86","t":"08:07:31","h":"Ouest","s":"25S-H54S000S-82-S"},{"r":"86","t":"08:08:52","h":"Ouest","s":"25N-H54N000A-80-A"},{"r":"86","t":"08:08:52","h":"Ouest","s":"25N-H54NV10A-80-A"},{"r":"86","t":"08:08:52","h":"Ouest","s":"25N-H54NV20A-80-A"},{"r":"86","t":"08:08:52","h":"Ouest","s":"25S-H54S000A-83-A"},{"r":"86","t":"08:31:52","h":"Ouest","s":"25N-H54N000I-80-I"},{"r":"86","t":"08:31:52","h":"Ouest","s":"25N-H54N100F-80-F1"},{"r":"86","t":"08:31:52","h":"Ouest","s":"25N-H54N200F-80-F2"},{"r":"86","t":"08:31:52","h":"Ouest","s":"25N-H54N300F-80-F3"},{"r":"86","t":"08:31:52","h":"Ouest","s":"25N-H54N400F-80-F4"},{"r":"86","t":"08:31:52","h":"Ouest","s":"25N-H54NV10I-80-I"},{"r":"86","t":"08:31:52","h":"Ouest","s":"25N-H54NV20I-80-I"},{"r":"86","t":"08:31:52","h":"Ouest","s":"25S-H54S000I-82-I"},{"r":"86","t":"08:31:52","h":"Ouest","s":"25S-H54S100F-80-F1"},{"r":"86","t":"08:31:52","h":"Ouest","s":"25S-H54S200F-80-F2"},{"r":"86","t":"08:38:31","h":"Ouest","s":"25N-H54N000S-80-S"},{"r":"86","t":"08:38:31","h":"Ouest","s":"25N-H54NV10S-82-S"},{"r":"86","t":"08:38:31","h":"Ouest","s":"25N-H54NV20S-80-S"},{"r":"86","t":"08:38:31","h":"Ouest","s":"25S-H54S000S-82-S"},{"r":"86","t":"08:40:52","h":"Ouest","s":"25N-H54N000A-80-A"},{"r":"86","t":"08:40:52","h":"Ouest","s":"25N-H54NV10A-80-A"},{"r":"86","t":"08:40:52","h":"Ouest","s":"25N-H54NV20A-80-A"},{"r":"86","t":"08:40:52","h":"Ouest","s":"25S-H54S000A-83-A"},{"r":"86","t":"09:02:52","h":"Ouest","s":"25N-H54N000I-80-I"},{"r":"86","t":"09:02:52","h":"Ouest","s":"25N-H54N100F-80-F1"},{"r":"86","t":"09:02:52","h":"Ouest","s":"25N-H54N200F-80-F2"},{"r":"86","t":"09:02:52","h":"Ouest","s":"25N-H54N300F-80-F3"},{"r":"86","t":"09:02:52","h":"Ouest","s":"25N-H54N400F-80-F4"},{"r":"86","t":"09:02:52","h":"Ouest","s":"25N-H54NV10I-80-I"},{"r":"86","t":"09:02:52","h":"Ouest","s":"25N-H54NV20I-80-I"},{"r":"86","t":"09:02:52","h":"Ouest","s":"25S-H54S000I-82-I"},{"r":"86","t":"09:02:52","h":"Ouest","s":"25S-H54S100F-80-F1"},{"r":"86","t":"09:02:52","h":"Ouest","s":"25S-H54S200F-80-F2"},{"r":"86","t":"09:07:52","h":"Ouest","s":"25N-H54N000S-80-S"},{"r":"86","t":"09:07:52","h":"Ouest","s":"25N-H54NV10S-82-S"},{"r":"86","t":"09:07:52","h":"Ouest","s":"25N-H54NV20S-80-S"},{"r":"86","t":"09:07:52","h":"Ouest","s":"25S-H54S000S-82-S"},{"r":"86","t":"09:12:52","h":"Ouest","s":"25N-H54N000A-80-A"},{"r":"86","t":"09:12:52","h":"Ouest","s":"25N-H54NV10A-80-A"},{"r":"86","t":"09:12:52","h":"Ouest","s":"25N-H54NV20A-80-A"},{"r":"86","t":"09:12:52","h":"Ouest","s":"25S-H54S000A-83-A"},{"r":"86","t":"09:35:52","h":"Ouest","s":"25N-H54N000I-80-I"},{"r":"86","t":"09:35:52","h":"Ouest","s":"25N-H54N100F-80-F1"},{"r":"86","t":"09:35:52","h":"Ouest","s":"25N-H54N200F-80-F2"},{"r":"86","t":"09:35:52","h":"Ouest","s":"25N-H54N300F-80-F3"},{"r":"86","t":"09:35:52","h":"Ouest","s":"25N-H54N400F-80-F4"},{"r":"86","t":"09:35:52","h":"Ouest","s":"25N-H54NV10I-80-I"},{"r":"86","t":"09:35:52","h":"Ouest","s":"25N-H54NV20I-80-I"},{"r":"86","t":"09:35:52","h":"Ouest","s":"25S-H54S000I-82-I"},{"r":"86","t":"09:35:52","h":"Ouest","s":"25S-H54S100F-80-F1"},{"r":"86","t":"09:35:52","h":"Ouest","s":"25S-H54S200F-80-F2"},{"r":"86","t":"09:37:52","h":"Ouest","s":"25N-H54N000S-80-S"},{"r":"86","t":"09:37:52","h":"Ouest","s":"25N-H54NV10S-82-S"},{"r":"86","t":"09:37:52","h":"Ouest","s":"25N-H54NV20S-80-S"},{"r":"86","t":"09:37:52","h":"Ouest","s":"25S-H54S000S-82-S"},{"r":"86","t":"09:44:52","h":"Ouest","s":"25N-H54N000A-80-A"},{"r":"86","t":"09:44:52","h":"Ouest","s":"25N-H54NV10A-80-A"},{"r":"86","t":"09:44:52","h":"Ouest","s":"25N-H54NV20A-80-A"},{"r":"86","t":"09:44:52","h":"Ouest","s":"25S-H54S000A-83-A"},{"r":"86","t":"10:08:52","h":"Ouest","s":"25N-H54N000I-80-I"},{"r":"86","t":"10:08:52","h":"Ouest","s":"25N-H54N000S-80-S"},{"r":"86","t":"10:08:52","h":"Ouest","s":"25N-H54N100F-80-F1"},{"r":"86","t":"10:08:52","h":"Ouest","s":"25N-H54N200F-80-F2"},{"r":"86","t":"10:08:52","h":"Ouest","s":"25N-H54N300F-80-F3"},{"r":"86","t":"10:08:52","h":"Ouest","s":"25N-H54N400F-80-F4"},{"r":"86","t":"10:08:52","h":"Ouest","s":"25N-H54NV10I-80-I"},{"r":"86","t":"10:08:52","h":"Ouest","s":"25N-H54NV10S-82-S"},{"r":"86","t":"10:08:52","h":"Ouest","s":"25N-H54NV20I-80-I"},{"r":"86","t":"10:08:52","h":"Ouest","s":"25N-H54NV20S-80-S"},{"r":"86","t":"10:08:52","h":"Ouest","s":"25S-H54S000I-82-I"},{"r":"86","t":"10:08:52","h":"Ouest","s":"25S-H54S000S-82-S"},{"r":"86","t":"10:08:52","h":"Ouest","s":"25S-H54S100F-80-F1"},{"r":"86","t":"10:08:52","h":"Ouest","s":"25S-H54S200F-80-F2"},{"r":"86","t":"10:18:52","h":"Ouest","s":"25N-H54N000A-80-A"},{"r":"86","t":"10:18:52","h":"Ouest","s":"25N-H54NV10A-80-A"},{"r":"86","t":"10:18:52","h":"Ouest","s":"25N-H54NV20A-80-A"},{"r":"86","t":"10:18:52","h":"Ouest","s":"25S-H54S000A-83-A"},{"r":"86","t":"10:35:52","h":"Ouest","s":"25N-H54N000S-80-S"},{"r":"86","t":"10:35:52","h":"Ouest","s":"25N-H54NV10S-82-S"},{"r":"86","t":"10:35:52","h":"Ouest","s":"25N-H54NV20S-80-S"},{"r":"86","t":"10:35:52","h":"Ouest","s":"25S-H54S000S-82-S"},{"r":"86","t":"10:44:52","h":"Ouest","s":"25N-H54N000I-80-I"},{"r":"86","t":"10:44:52","h":"Ouest","s":"25N-H54N100F-80-F1"},{"r":"86","t":"10:44:52","h":"Ouest","s":"25N-H54N200F-80-F2"},{"r":"86","t":"10:44:52","h":"Ouest","s":"25N-H54N300F-80-F3"},{"r":"86","t":"10:44:52","h":"Ouest","s":"25N-H54N400F-80-F4"},{"r":"86","t":"10:44:52","h":"Ouest","s":"25N-H54NV10I-80-I"},{"r":"86","t":"10:44:52","h":"Ouest","s":"25N-H54NV20I-80-I"},{"r":"86","t":"10:44:52","h":"Ouest","s":"25S-H54S000I-82-I"},{"r":"86","t":"10:44:52","h":"Ouest","s":"25S-H54S100F-80-F1"},{"r":"86","t":"10:44:52","h":"Ouest","s":"25S-H54S200F-80-F2"},{"r":"86","t":"10:51:52","h":"Ouest","s":"25N-H54N000A-80-A"},{"r":"86","t":"10:51:52","h":"Ouest","s":"25N-H54NV10A-80-A"},{"r":"86","t":"10:51:52","h":"Ouest","s":"25N-H54NV20A-80-A"},{"r":"86","t":"10:51:52","h":"Ouest","s":"25S-H54S000A-83-A"},{"r":"86","t":"11:03:52","h":"Ouest","s":"25N-H54N000S-80-S"},{"r":"86","t":"11:03:52","h":"Ouest","s":"25N-H54NV10S-82-S"},{"r":"86","t":"11:03:52","h":"Ouest","s":"25N-H54NV20S-80-S"},{"r":"86","t":"11:03:52","h":"Ouest","s":"25S-H54S000S-82-S"},{"r":"86","t":"11:17:52","h":"Ouest","s":"25N-H54N000I-80-I"},{"r":"86","t":"11:17:52","h":"Ouest","s":"25N-H54N100F-80-F1"},{"r":"86","t":"11:17:52","h":"Ouest","s":"25N-H54N200F-80-F2"},{"r":"86","t":"11:17:52","h":"Ouest","s":"25N-H54N300F-80-F3"},{"r":"86","t":"11:17:52","h":"Ouest","s":"25N-H54N400F-80-F4"},{"r":"86","t":"11:17:52","h":"Ouest","s":"25N-H54NV10I-80-I"},{"r":"86","t":"11:17:52","h":"Ouest","s":"25N-H54NV20I-80-I"},{"r":"86","t":"11:17:52","h":"Ouest","s":"25S-H54S000I-82-I"},{"r":"86","t":"11:17:52","h":"Ouest","s":"25S-H54S100F-80-F1"},{"r":"86","t":"11:17:52","h":"Ouest","s":"25S-H54S200F-80-F2"},{"r":"86","t":"11:24:52","h":"Ouest","s":"25N-H54N000A-80-A"},{"r":"86","t":"11:24:52","h":"Ouest","s":"25N-H54NV10A-80-A"},{"r":"86","t":"11:24:52","h":"Ouest","s":"25N-H54NV20A-80-A"},{"r":"86","t":"11:24:52","h":"Ouest","s":"25S-H54S000A-83-A"},{"r":"86","t":"11:31:52","h":"Ouest","s":"25N-H54N000S-80-S"},{"r":"86","t":"11:31:52","h":"Ouest","s":"25N-H54NV10S-82-S"},{"r":"86","t":"11:31:52","h":"Ouest","s":"25N-H54NV20S-80-S"},{"r":"86","t":"11:31:52","h":"Ouest","s":"25S-H54S000S-82-S"},{"r":"86","t":"11:50:52","h":"Ouest","s":"25N-H54N000I-80-I"},{"r":"86","t":"11:50:52","h":"Ouest","s":"25N-H54N100F-80-F1"},{"r":"86","t":"11:50:52","h":"Ouest","s":"25N-H54N200F-80-F2"},{"r":"86","t":"11:50:52","h":"Ouest","s":"25N-H54N300F-80-F3"},{"r":"86","t":"11:50:52","h":"Ouest","s":"25N-H54N400F-80-F4"},{"r":"86","t":"11:50:52","h":"Ouest","s":"25N-H54NV10I-80-I"},{"r":"86","t":"11:50:52","h":"Ouest","s":"25N-H54NV20I-80-I"},{"r":"86","t":"11:50:52","h":"Ouest","s":"25S-H54S000I-82-I"},{"r":"86","t":"11:50:52","h":"Ouest","s":"25S-H54S100F-80-F1"},{"r":"86","t":"11:50:52","h":"Ouest","s":"25S-H54S200F-80-F2"},{"r":"86","t":"11:57:52","h":"Ouest","s":"25N-H54N000A-80-A"},{"r":"86","t":"11:57:52","h":"Ouest","s":"25N-H54NV10A-80-A"},{"r":"86","t":"11:57:52","h":"Ouest","s":"25N-H54NV20A-80-A"},{"r":"86","t":"11:57:52","h":"Ouest","s":"25S-H54S000A-83-A"},{"r":"86","t":"12:02:52","h":"Ouest","s":"25N-H54N000S-80-S"},{"r":"86","t":"12:02:52","h":"Ouest","s":"25N-H54NV10S-82-S"},{"r":"86","t":"12:02:52","h":"Ouest","s":"25N-H54NV20S-80-S"},{"r":"86","t":"12:02:52","h":"Ouest","s":"25S-H54S000S-82-S"},{"r":"86","t":"12:23:52","h":"Ouest","s":"25N-H54N000I-80-I"},{"r":"86","t":"12:23:52","h":"Ouest","s":"25N-H54N100F-80-F1"},{"r":"86","t":"12:23:52","h":"Ouest","s":"25N-H54N200F-80-F2"},{"r":"86","t":"12:23:52","h":"Ouest","s":"25N-H54N300F-80-F3"},{"r":"86","t":"12:23:52","h":"Ouest","s":"25N-H54N400F-80-F4"},{"r":"86","t":"12:23:52","h":"Ouest","s":"25N-H54NV10I-80-I"},{"r":"86","t":"12:23:52","h":"Ouest","s":"25N-H54NV20I-80-I"},{"r":"86","t":"12:23:52","h":"Ouest","s":"25S-H54S000I-82-I"},{"r":"86","t":"12:23:52","h":"Ouest","s":"25S-H54S100F-80-F1"},{"r":"86","t":"12:23:52","h":"Ouest","s":"25S-H54S200F-80-F2"},{"r":"86","t":"12:30:52","h":"Ouest","s":"25N-H54N000A-80-A"},{"r":"86","t":"12:30:52","h":"Ouest","s":"25N-H54NV10A-80-A"},{"r":"86","t":"12:30:52","h":"Ouest","s":"25N-H54NV20A-80-A"},{"r":"86","t":"12:30:52","h":"Ouest","s":"25S-H54S000A-83-A"},{"r":"86","t":"12:35:52","h":"Ouest","s":"25N-H54N000S-80-S"},{"r":"86","t":"12:35:52","h":"Ouest","s":"25N-H54NV10S-82-S"},{"r":"86","t":"12:35:52","h":"Ouest","s":"25N-H54NV20S-80-S"},{"r":"86","t":"12:35:52","h":"Ouest","s":"25S-H54S000S-82-S"},{"r":"86","t":"12:56:52","h":"Ouest","s":"25N-H54N000I-80-I"},{"r":"86","t":"12:56:52","h":"Ouest","s":"25N-H54N100F-80-F1"},{"r":"86","t":"12:56:52","h":"Ouest","s":"25N-H54N200F-80-F2"},{"r":"86","t":"12:56:52","h":"Ouest","s":"25N-H54N300F-80-F3"},{"r":"86","t":"12:56:52","h":"Ouest","s":"25N-H54N400F-80-F4"},{"r":"86","t":"12:56:52","h":"Ouest","s":"25N-H54NV10I-80-I"},{"r":"86","t":"12:56:52","h":"Ouest","s":"25N-H54NV20I-80-I"},{"r":"86","t":"12:56:52","h":"Ouest","s":"25S-H54S000I-82-I"},{"r":"86","t":"12:56:52","h":"Ouest","s":"25S-H54S100F-80-F1"},{"r":"86","t":"12:56:52","h":"Ouest","s":"25S-H54S200F-80-F2"},{"r":"86","t":"13:03:52","h":"Ouest","s":"25N-H54N000A-80-A"},{"r":"86","t":"13:03:52","h":"Ouest","s":"25N-H54NV10A-80-A"},{"r":"86","t":"13:03:52","h":"Ouest","s":"25N-H54NV20A-80-A"},{"r":"86","t":"13:03:52","h":"Ouest","s":"25S-H54S000A-83-A"},{"r":"86","t":"13:04:52","h":"Ouest","s":"25N-H54N000S-80-S"},{"r":"86","t":"13:04:52","h":"Ouest","s":"25N-H54NV10S-82-S"},{"r":"86","t":"13:04:52","h":"Ouest","s":"25N-H54NV20S-80-S"},{"r":"86","t":"13:04:52","h":"Ouest","s":"25S-H54S000S-82-S"},{"r":"86","t":"13:29:52","h":"Ouest","s":"25N-H54N000I-80-I"},{"r":"86","t":"13:29:52","h":"Ouest","s":"25N-H54N100F-80-F1"},{"r":"86","t":"13:29:52","h":"Ouest","s":"25N-H54N200F-80-F2"},{"r":"86","t":"13:29:52","h":"Ouest","s":"25N-H54N300F-80-F3"},{"r":"86","t":"13:29:52","h":"Ouest","s":"25N-H54N400F-80-F4"},{"r":"86","t":"13:29:52","h":"Ouest","s":"25N-H54NV10I-80-I"},{"r":"86","t":"13:29:52","h":"Ouest","s":"25N-H54NV20I-80-I"},{"r":"86","t":"13:29:52","h":"Ouest","s":"25S-H54S000I-82-I"},{"r":"86","t":"13:29:52","h":"Ouest","s":"25S-H54S100F-80-F1"},{"r":"86","t":"13:29:52","h":"Ouest","s":"25S-H54S200F-80-F2"},{"r":"86","t":"13:33:52","h":"Ouest","s":"25N-H54N000S-80-S"},{"r":"86","t":"13:33:52","h":"Ouest","s":"25N-H54NV10S-82-S"},{"r":"86","t":"13:33:52","h":"Ouest","s":"25N-H54NV20S-80-S"},{"r":"86","t":"13:33:52","h":"Ouest","s":"25S-H54S000S-82-S"},{"r":"86","t":"13:37:52","h":"Ouest","s":"25N-H54N000A-80-A"},{"r":"86","t":"13:37:52","h":"Ouest","s":"25N-H54NV10A-80-A"},{"r":"86","t":"13:37:52","h":"Ouest","s":"25N-H54NV20A-80-A"},{"r":"86","t":"13:37:52","h":"Ouest","s":"25S-H54S000A-83-A"},{"r":"86","t":"14:01:52","h":"Ouest","s":"25N-H54N000I-80-I"},{"r":"86","t":"14:01:52","h":"Ouest","s":"25N-H54N100F-80-F1"},{"r":"86","t":"14:01:52","h":"Ouest","s":"25N-H54N200F-80-F2"},{"r":"86","t":"14:01:52","h":"Ouest","s":"25N-H54N300F-80-F3"},{"r":"86","t":"14:01:52","h":"Ouest","s":"25N-H54N400F-80-F4"},{"r":"86","t":"14:01:52","h":"Ouest","s":"25N-H54NV10I-80-I"},{"r":"86","t":"14:01:52","h":"Ouest","s":"25N-H54NV20I-80-I"},{"r":"86","t":"14:01:52","h":"Ouest","s":"25S-H54S000I-82-I"},{"r":"86","t":"14:01:52","h":"Ouest","s":"25S-H54S100F-80-F1"},{"r":"86","t":"14:01:52","h":"Ouest","s":"25S-H54S200F-80-F2"},{"r":"86","t":"14:03:52","h":"Ouest","s":"25N-H54N000S-80-S"},{"r":"86","t":"14:03:52","h":"Ouest","s":"25N-H54NV10S-82-S"},{"r":"86","t":"14:03:52","h":"Ouest","s":"25N-H54NV20S-80-S"},{"r":"86","t":"14:03:52","h":"Ouest","s":"25S-H54S000S-82-S"},{"r":"86","t":"14:12:52","h":"Ouest","s":"25N-H54N000A-80-A"},{"r":"86","t":"14:12:52","h":"Ouest","s":"25N-H54NV10A-80-A"},{"r":"86","t":"14:12:52","h":"Ouest","s":"25N-H54NV20A-80-A"},{"r":"86","t":"14:12:52","h":"Ouest","s":"25S-H54S000A-83-A"},{"r":"86","t":"14:33:52","h":"Ouest","s":"25N-H54N000I-80-I"},{"r":"86","t":"14:33:52","h":"Ouest","s":"25N-H54N000S-80-S"},{"r":"86","t":"14:33:52","h":"Ouest","s":"25N-H54N100F-80-F1"},{"r":"86","t":"14:33:52","h":"Ouest","s":"25N-H54N200F-80-F2"},{"r":"86","t":"14:33:52","h":"Ouest","s":"25N-H54N300F-80-F3"},{"r":"86","t":"14:33:52","h":"Ouest","s":"25N-H54N400F-80-F4"},{"r":"86","t":"14:33:52","h":"Ouest","s":"25N-H54NV10I-80-I"},{"r":"86","t":"14:33:52","h":"Ouest","s":"25N-H54NV10S-82-S"},{"r":"86","t":"14:33:52","h":"Ouest","s":"25N-H54NV20I-80-I"},{"r":"86","t":"14:33:52","h":"Ouest","s":"25N-H54NV20S-80-S"},{"r":"86","t":"14:33:52","h":"Ouest","s":"25S-H54S000I-82-I"},{"r":"86","t":"14:33:52","h":"Ouest","s":"25S-H54S000S-82-S"},{"r":"86","t":"14:33:52","h":"Ouest","s":"25S-H54S100F-80-F1"},{"r":"86","t":"14:33:52","h":"Ouest","s":"25S-H54S200F-80-F2"},{"r":"86","t":"14:44:52","h":"Ouest","s":"25N-H54N000A-80-A"},{"r":"86","t":"14:44:52","h":"Ouest","s":"25N-H54NV10A-80-A"},{"r":"86","t":"14:44:52","h":"Ouest","s":"25N-H54NV20A-80-A"},{"r":"86","t":"14:44:52","h":"Ouest","s":"25S-H54S000A-83-A"},{"r":"86","t":"15:02:52","h":"Ouest","s":"25N-H54N000S-80-S"},{"r":"86","t":"15:02:52","h":"Ouest","s":"25N-H54NV10S-82-S"},{"r":"86","t":"15:02:52","h":"Ouest","s":"25N-H54NV20S-80-S"},{"r":"86","t":"15:02:52","h":"Ouest","s":"25S-H54S000S-82-S"},{"r":"86","t":"15:05:52","h":"Ouest","s":"25N-H54N000I-80-I"},{"r":"86","t":"15:05:52","h":"Ouest","s":"25N-H54N100F-80-F1"},{"r":"86","t":"15:05:52","h":"Ouest","s":"25N-H54N200F-80-F2"},{"r":"86","t":"15:05:52","h":"Ouest","s":"25N-H54N300F-80-F3"},{"r":"86","t":"15:05:52","h":"Ouest","s":"25N-H54N400F-80-F4"},{"r":"86","t":"15:05:52","h":"Ouest","s":"25N-H54NV10I-80-I"},{"r":"86","t":"15:05:52","h":"Ouest","s":"25N-H54NV20I-80-I"},{"r":"86","t":"15:05:52","h":"Ouest","s":"25S-H54S000I-82-I"},{"r":"86","t":"15:05:52","h":"Ouest","s":"25S-H54S100F-80-F1"},{"r":"86","t":"15:05:52","h":"Ouest","s":"25S-H54S200F-80-F2"},{"r":"86","t":"15:17:52","h":"Ouest","s":"25N-H54N000A-80-A"},{"r":"86","t":"15:17:52","h":"Ouest","s":"25N-H54NV10A-80-A"},{"r":"86","t":"15:17:52","h":"Ouest","s":"25N-H54NV20A-80-A"},{"r":"86","t":"15:17:52","h":"Ouest","s":"25S-H54S000A-83-A"},{"r":"86","t":"15:30:52","h":"Ouest","s":"25N-H54N000S-80-S"},{"r":"86","t":"15:30:52","h":"Ouest","s":"25N-H54NV10S-82-S"},{"r":"86","t":"15:30:52","h":"Ouest","s":"25N-H54NV20S-80-S"},{"r":"86","t":"15:30:52","h":"Ouest","s":"25S-H54S000S-82-S"},{"r":"86","t":"15:37:52","h":"Ouest","s":"25N-H54N000I-80-I"},{"r":"86","t":"15:37:52","h":"Ouest","s":"25N-H54N100F-80-F1"},{"r":"86","t":"15:37:52","h":"Ouest","s":"25N-H54N200F-80-F2"},{"r":"86","t":"15:37:52","h":"Ouest","s":"25N-H54N300F-80-F3"},{"r":"86","t":"15:37:52","h":"Ouest","s":"25N-H54N400F-80-F4"},{"r":"86","t":"15:37:52","h":"Ouest","s":"25N-H54NV10I-80-I"},{"r":"86","t":"15:37:52","h":"Ouest","s":"25N-H54NV20I-80-I"},{"r":"86","t":"15:37:52","h":"Ouest","s":"25S-H54S000I-82-I"},{"r":"86","t":"15:37:52","h":"Ouest","s":"25S-H54S100F-80-F1"},{"r":"86","t":"15:37:52","h":"Ouest","s":"25S-H54S200F-80-F2"},{"r":"86","t":"15:50:52","h":"Ouest","s":"25N-H54N000A-80-A"},{"r":"86","t":"15:50:52","h":"Ouest","s":"25N-H54NV10A-80-A"},{"r":"86","t":"15:50:52","h":"Ouest","s":"25N-H54NV20A-80-A"},{"r":"86","t":"15:50:52","h":"Ouest","s":"25S-H54S000A-83-A"},{"r":"86","t":"16:02:31","h":"Ouest","s":"25N-H54N000S-80-S"},{"r":"86","t":"16:02:31","h":"Ouest","s":"25N-H54NV10S-82-S"},{"r":"86","t":"16:02:31","h":"Ouest","s":"25N-H54NV20S-80-S"},{"r":"86","t":"16:02:31","h":"Ouest","s":"25S-H54S000S-82-S"},{"r":"86","t":"16:09:52","h":"Ouest","s":"25N-H54N000I-80-I"},{"r":"86","t":"16:09:52","h":"Ouest","s":"25N-H54N100F-80-F1"},{"r":"86","t":"16:09:52","h":"Ouest","s":"25N-H54N200F-80-F2"},{"r":"86","t":"16:09:52","h":"Ouest","s":"25N-H54N300F-80-F3"},{"r":"86","t":"16:09:52","h":"Ouest","s":"25N-H54N400F-80-F4"},{"r":"86","t":"16:09:52","h":"Ouest","s":"25N-H54NV10I-80-I"},{"r":"86","t":"16:09:52","h":"Ouest","s":"25N-H54NV20I-80-I"},{"r":"86","t":"16:09:52","h":"Ouest","s":"25S-H54S000I-82-I"},{"r":"86","t":"16:09:52","h":"Ouest","s":"25S-H54S100F-80-F1"},{"r":"86","t":"16:09:52","h":"Ouest","s":"25S-H54S200F-80-F2"},{"r":"86","t":"16:22:52","h":"Ouest","s":"25N-H54N000A-80-A"},{"r":"86","t":"16:22:52","h":"Ouest","s":"25N-H54NV10A-80-A"},{"r":"86","t":"16:22:52","h":"Ouest","s":"25N-H54NV20A-80-A"},{"r":"86","t":"16:22:52","h":"Ouest","s":"25S-H54S000A-83-A"},{"r":"86","t":"16:37:31","h":"Ouest","s":"25N-H54N000S-80-S"},{"r":"86","t":"16:37:31","h":"Ouest","s":"25N-H54NV10S-82-S"},{"r":"86","t":"16:37:31","h":"Ouest","s":"25N-H54NV20S-80-S"},{"r":"86","t":"16:37:31","h":"Ouest","s":"25S-H54S000S-82-S"},{"r":"86","t":"16:41:52","h":"Ouest","s":"25N-H54N000I-80-I"},{"r":"86","t":"16:41:52","h":"Ouest","s":"25N-H54N100F-80-F1"},{"r":"86","t":"16:41:52","h":"Ouest","s":"25N-H54N200F-80-F2"},{"r":"86","t":"16:41:52","h":"Ouest","s":"25N-H54N300F-80-F3"},{"r":"86","t":"16:41:52","h":"Ouest","s":"25N-H54N400F-80-F4"},{"r":"86","t":"16:41:52","h":"Ouest","s":"25N-H54NV10I-80-I"},{"r":"86","t":"16:41:52","h":"Ouest","s":"25N-H54NV20I-80-I"},{"r":"86","t":"16:41:52","h":"Ouest","s":"25S-H54S000I-82-I"},{"r":"86","t":"16:41:52","h":"Ouest","s":"25S-H54S100F-80-F1"},{"r":"86","t":"16:41:52","h":"Ouest","s":"25S-H54S200F-80-F2"},{"r":"86","t":"16:55:52","h":"Ouest","s":"25N-H54N000A-80-A"},{"r":"86","t":"16:55:52","h":"Ouest","s":"25N-H54NV10A-80-A"},{"r":"86","t":"16:55:52","h":"Ouest","s":"25N-H54NV20A-80-A"},{"r":"86","t":"16:55:52","h":"Ouest","s":"25S-H54S000A-83-A"},{"r":"86","t":"17:13:52","h":"Ouest","s":"25N-H54N000I-80-I"},{"r":"86","t":"17:13:52","h":"Ouest","s":"25N-H54N000S-80-S"},{"r":"86","t":"17:13:52","h":"Ouest","s":"25N-H54N100F-80-F1"},{"r":"86","t":"17:13:52","h":"Ouest","s":"25N-H54N200F-80-F2"},{"r":"86","t":"17:13:52","h":"Ouest","s":"25N-H54N300F-80-F3"},{"r":"86","t":"17:13:52","h":"Ouest","s":"25N-H54N400F-80-F4"},{"r":"86","t":"17:13:52","h":"Ouest","s":"25N-H54NV10I-80-I"},{"r":"86","t":"17:13:52","h":"Ouest","s":"25N-H54NV10S-82-S"},{"r":"86","t":"17:13:52","h":"Ouest","s":"25N-H54NV20I-80-I"},{"r":"86","t":"17:13:52","h":"Ouest","s":"25N-H54NV20S-80-S"},{"r":"86","t":"17:13:52","h":"Ouest","s":"25S-H54S000I-82-I"},{"r":"86","t":"17:13:52","h":"Ouest","s":"25S-H54S000S-82-S"},{"r":"86","t":"17:13:52","h":"Ouest","s":"25S-H54S100F-80-F1"},{"r":"86","t":"17:13:52","h":"Ouest","s":"25S-H54S200F-80-F2"},{"r":"86","t":"17:27:52","h":"Ouest","s":"25N-H54N000A-80-A"},{"r":"86","t":"17:27:52","h":"Ouest","s":"25N-H54NV10A-80-A"},{"r":"86","t":"17:27:52","h":"Ouest","s":"25N-H54NV20A-80-A"},{"r":"86","t":"17:27:52","h":"Ouest","s":"25S-H54S000A-83-A"},{"r":"86","t":"17:40:52","h":"Ouest","s":"25N-H54N000S-80-S"},{"r":"86","t":"17:40:52","h":"Ouest","s":"25N-H54NV10S-82-S"},{"r":"86","t":"17:40:52","h":"Ouest","s":"25N-H54NV20S-80-S"},{"r":"86","t":"17:40:52","h":"Ouest","s":"25S-H54S000S-82-S"},{"r":"86","t":"17:46:52","h":"Ouest","s":"25N-H54N000I-80-I"},{"r":"86","t":"17:46:52","h":"Ouest","s":"25N-H54N100F-80-F1"},{"r":"86","t":"17:46:52","h":"Ouest","s":"25N-H54N200F-80-F2"},{"r":"86","t":"17:46:52","h":"Ouest","s":"25N-H54N300F-80-F3"},{"r":"86","t":"17:46:52","h":"Ouest","s":"25N-H54N400F-80-F4"},{"r":"86","t":"17:46:52","h":"Ouest","s":"25N-H54NV10I-80-I"},{"r":"86","t":"17:46:52","h":"Ouest","s":"25N-H54NV20I-80-I"},{"r":"86","t":"17:46:52","h":"Ouest","s":"25S-H54S000I-82-I"},{"r":"86","t":"17:46:52","h":"Ouest","s":"25S-H54S100F-80-F1"},{"r":"86","t":"17:46:52","h":"Ouest","s":"25S-H54S200F-80-F2"},{"r":"86","t":"17:59:52","h":"Ouest","s":"25N-H54N000A-80-A"},{"r":"86","t":"17:59:52","h":"Ouest","s":"25N-H54NV10A-80-A"},{"r":"86","t":"17:59:52","h":"Ouest","s":"25N-H54NV20A-80-A"},{"r":"86","t":"17:59:52","h":"Ouest","s":"25S-H54S000A-83-A"},{"r":"86","t":"18:09:52","h":"Ouest","s":"25N-H54N000S-80-S"},{"r":"86","t":"18:09:52","h":"Ouest","s":"25N-H54NV10S-82-S"},{"r":"86","t":"18:09:52","h":"Ouest","s":"25N-H54NV20S-80-S"},{"r":"86","t":"18:09:52","h":"Ouest","s":"25S-H54S000S-82-S"},{"r":"86","t":"18:16:52","h":"Ouest","s":"25N-H54N000I-80-I"},{"r":"86","t":"18:16:52","h":"Ouest","s":"25N-H54N100F-80-F1"},{"r":"86","t":"18:16:52","h":"Ouest","s":"25N-H54N200F-80-F2"},{"r":"86","t":"18:16:52","h":"Ouest","s":"25N-H54N300F-80-F3"},{"r":"86","t":"18:16:52","h":"Ouest","s":"25N-H54N400F-80-F4"},{"r":"86","t":"18:16:52","h":"Ouest","s":"25N-H54NV10I-80-I"},{"r":"86","t":"18:16:52","h":"Ouest","s":"25N-H54NV20I-80-I"},{"r":"86","t":"18:16:52","h":"Ouest","s":"25S-H54S000I-82-I"},{"r":"86","t":"18:16:52","h":"Ouest","s":"25S-H54S100F-80-F1"},{"r":"86","t":"18:16:52","h":"Ouest","s":"25S-H54S200F-80-F2"},{"r":"86","t":"18:32:52","h":"Ouest","s":"25N-H54N000A-80-A"},{"r":"86","t":"18:32:52","h":"Ouest","s":"25N-H54NV10A-80-A"},{"r":"86","t":"18:32:52","h":"Ouest","s":"25N-H54NV20A-80-A"},{"r":"86","t":"18:32:52","h":"Ouest","s":"25S-H54S000A-83-A"},{"r":"86","t":"18:41:52","h":"Ouest","s":"25N-H54N000S-80-S"},{"r":"86","t":"18:41:52","h":"Ouest","s":"25N-H54NV10S-82-S"},{"r":"86","t":"18:41:52","h":"Ouest","s":"25N-H54NV20S-80-S"},{"r":"86","t":"18:41:52","h":"Ouest","s":"25S-H54S000S-82-S"},{"r":"86","t":"18:49:52","h":"Ouest","s":"25N-H54N000I-80-I"},{"r":"86","t":"18:49:52","h":"Ouest","s":"25N-H54N100F-80-F1"},{"r":"86","t":"18:49:52","h":"Ouest","s":"25N-H54N200F-80-F2"},{"r":"86","t":"18:49:52","h":"Ouest","s":"25N-H54N300F-80-F3"},{"r":"86","t":"18:49:52","h":"Ouest","s":"25N-H54N400F-80-F4"},{"r":"86","t":"18:49:52","h":"Ouest","s":"25N-H54NV10I-80-I"},{"r":"86","t":"18:49:52","h":"Ouest","s":"25N-H54NV20I-80-I"},{"r":"86","t":"18:49:52","h":"Ouest","s":"25S-H54S000I-82-I"},{"r":"86","t":"18:49:52","h":"Ouest","s":"25S-H54S100F-80-F1"},{"r":"86","t":"18:49:52","h":"Ouest","s":"25S-H54S200F-80-F2"},{"r":"86","t":"19:05:52","h":"Ouest","s":"25N-H54N000A-80-A"},{"r":"86","t":"19:05:52","h":"Ouest","s":"25N-H54NV10A-80-A"},{"r":"86","t":"19:05:52","h":"Ouest","s":"25N-H54NV20A-80-A"},{"r":"86","t":"19:05:52","h":"Ouest","s":"25S-H54S000A-83-A"},{"r":"86","t":"19:11:52","h":"Ouest","s":"25N-H54N000S-80-S"},{"r":"86","t":"19:11:52","h":"Ouest","s":"25N-H54NV10S-82-S"},{"r":"86","t":"19:11:52","h":"Ouest","s":"25N-H54NV20S-80-S"},{"r":"86","t":"19:11:52","h":"Ouest","s":"25S-H54S000S-82-S"},{"r":"86","t":"19:22:52","h":"Ouest","s":"25N-H54N000I-80-I"},{"r":"86","t":"19:22:52","h":"Ouest","s":"25N-H54N100F-80-F1"},{"r":"86","t":"19:22:52","h":"Ouest","s":"25N-H54N200F-80-F2"},{"r":"86","t":"19:22:52","h":"Ouest","s":"25N-H54N300F-80-F3"},{"r":"86","t":"19:22:52","h":"Ouest","s":"25N-H54N400F-80-F4"},{"r":"86","t":"19:22:52","h":"Ouest","s":"25N-H54NV10I-80-I"},{"r":"86","t":"19:22:52","h":"Ouest","s":"25N-H54NV20I-80-I"},{"r":"86","t":"19:22:52","h":"Ouest","s":"25S-H54S000I-82-I"},{"r":"86","t":"19:22:52","h":"Ouest","s":"25S-H54S100F-80-F1"},{"r":"86","t":"19:22:52","h":"Ouest","s":"25S-H54S200F-80-F2"},{"r":"86","t":"19:38:52","h":"Ouest","s":"25N-H54N000A-80-A"},{"r":"86","t":"19:38:52","h":"Ouest","s":"25N-H54NV10A-80-A"},{"r":"86","t":"19:38:52","h":"Ouest","s":"25N-H54NV20A-80-A"},{"r":"86","t":"19:38:52","h":"Ouest","s":"25S-H54S000A-83-A"},{"r":"86","t":"19:40:52","h":"Ouest","s":"25N-H54N000S-80-S"},{"r":"86","t":"19:40:52","h":"Ouest","s":"25N-H54NV10S-82-S"},{"r":"86","t":"19:40:52","h":"Ouest","s":"25N-H54NV20S-80-S"},{"r":"86","t":"19:40:52","h":"Ouest","s":"25S-H54S000S-82-S"},{"r":"86","t":"19:53:52","h":"Ouest","s":"25N-H54N000I-80-I"},{"r":"86","t":"19:53:52","h":"Ouest","s":"25N-H54N100F-80-F1"},{"r":"86","t":"19:53:52","h":"Ouest","s":"25N-H54N200F-80-F2"},{"r":"86","t":"19:53:52","h":"Ouest","s":"25N-H54N300F-80-F3"},{"r":"86","t":"19:53:52","h":"Ouest","s":"25N-H54N400F-80-F4"},{"r":"86","t":"19:53:52","h":"Ouest","s":"25N-H54NV10I-80-I"},{"r":"86","t":"19:53:52","h":"Ouest","s":"25N-H54NV20I-80-I"},{"r":"86","t":"19:53:52","h":"Ouest","s":"25S-H54S000I-82-I"},{"r":"86","t":"19:53:52","h":"Ouest","s":"25S-H54S100F-80-F1"},{"r":"86","t":"19:53:52","h":"Ouest","s":"25S-H54S200F-80-F2"},{"r":"86","t":"20:08:52","h":"Ouest","s":"25N-H54N000A-80-A"},{"r":"86","t":"20:08:52","h":"Ouest","s":"25N-H54N000S-80-S"},{"r":"86","t":"20:08:52","h":"Ouest","s":"25N-H54NV10A-80-A"},{"r":"86","t":"20:08:52","h":"Ouest","s":"25N-H54NV10S-82-S"},{"r":"86","t":"20:08:52","h":"Ouest","s":"25N-H54NV20A-80-A"},{"r":"86","t":"20:08:52","h":"Ouest","s":"25N-H54NV20S-80-S"},{"r":"86","t":"20:08:52","h":"Ouest","s":"25S-H54S000A-83-A"},{"r":"86","t":"20:08:52","h":"Ouest","s":"25S-H54S000S-82-S"},{"r":"86","t":"20:24:52","h":"Ouest","s":"25N-H54N000I-80-I"},{"r":"86","t":"20:24:52","h":"Ouest","s":"25N-H54N100F-80-F1"},{"r":"86","t":"20:24:52","h":"Ouest","s":"25N-H54N200F-80-F2"},{"r":"86","t":"20:24:52","h":"Ouest","s":"25N-H54N300F-80-F3"},{"r":"86","t":"20:24:52","h":"Ouest","s":"25N-H54N400F-80-F4"},{"r":"86","t":"20:24:52","h":"Ouest","s":"25N-H54NV10I-80-I"},{"r":"86","t":"20:24:52","h":"Ouest","s":"25N-H54NV20I-80-I"},{"r":"86","t":"20:24:52","h":"Ouest","s":"25S-H54S000I-82-I"},{"r":"86","t":"20:24:52","h":"Ouest","s":"25S-H54S100F-80-F1"},{"r":"86","t":"20:24:52","h":"Ouest","s":"25S-H54S200F-80-F2"},{"r":"86","t":"20:35:52","h":"Ouest","s":"25N-H54N000S-80-S"},{"r":"86","t":"20:35:52","h":"Ouest","s":"25N-H54NV10S-82-S"},{"r":"86","t":"20:35:52","h":"Ouest","s":"25N-H54NV20S-80-S"},{"r":"86","t":"20:35:52","h":"Ouest","s":"25S-H54S000S-82-S"},{"r":"86","t":"20:41:52","h":"Ouest","s":"25N-H54N000A-80-A"},{"r":"86","t":"20:41:52","h":"Ouest","s":"25N-H54NV10A-80-A"},{"r":"86","t":"20:41:52","h":"Ouest","s":"25N-H54NV20A-80-A"},{"r":"86","t":"20:41:52","h":"Ouest","s":"25S-H54S000A-83-A"},{"r":"86","t":"20:55:52","h":"Ouest","s":"25N-H54N000I-80-I"},{"r":"86","t":"20:55:52","h":"Ouest","s":"25N-H54N100F-80-F1"},{"r":"86","t":"20:55:52","h":"Ouest","s":"25N-H54N200F-80-F2"},{"r":"86","t":"20:55:52","h":"Ouest","s":"25N-H54N300F-80-F3"},{"r":"86","t":"20:55:52","h":"Ouest","s":"25N-H54N400F-80-F4"},{"r":"86","t":"20:55:52","h":"Ouest","s":"25N-H54NV10I-80-I"},{"r":"86","t":"20:55:52","h":"Ouest","s":"25N-H54NV20I-80-I"},{"r":"86","t":"20:55:52","h":"Ouest","s":"25S-H54S000I-82-I"},{"r":"86","t":"20:55:52","h":"Ouest","s":"25S-H54S100F-80-F1"},{"r":"86","t":"20:55:52","h":"Ouest","s":"25S-H54S200F-80-F2"},{"r":"86","t":"21:04:52","h":"Ouest","s":"25N-H54N000S-80-S"},{"r":"86","t":"21:04:52","h":"Ouest","s":"25N-H54NV10S-82-S"},{"r":"86","t":"21:04:52","h":"Ouest","s":"25N-H54NV20S-80-S"},{"r":"86","t":"21:04:52","h":"Ouest","s":"25S-H54S000S-82-S"},{"r":"86","t":"21:14:52","h":"Ouest","s":"25N-H54N000A-80-A"},{"r":"86","t":"21:14:52","h":"Ouest","s":"25N-H54NV10A-80-A"},{"r":"86","t":"21:14:52","h":"Ouest","s":"25N-H54NV20A-80-A"},{"r":"86","t":"21:14:52","h":"Ouest","s":"25S-H54S000A-83-A"},{"r":"86","t":"21:26:52","h":"Ouest","s":"25N-H54N000I-80-I"},{"r":"86","t":"21:26:52","h":"Ouest","s":"25N-H54N100F-80-F1"},{"r":"86","t":"21:26:52","h":"Ouest","s":"25N-H54N200F-80-F2"},{"r":"86","t":"21:26:52","h":"Ouest","s":"25N-H54N300F-80-F3"},{"r":"86","t":"21:26:52","h":"Ouest","s":"25N-H54N400F-80-F4"},{"r":"86","t":"21:26:52","h":"Ouest","s":"25N-H54NV10I-80-I"},{"r":"86","t":"21:26:52","h":"Ouest","s":"25N-H54NV20I-80-I"},{"r":"86","t":"21:26:52","h":"Ouest","s":"25S-H54S000I-82-I"},{"r":"86","t":"21:26:52","h":"Ouest","s":"25S-H54S100F-80-F1"},{"r":"86","t":"21:26:52","h":"Ouest","s":"25S-H54S200F-80-F2"},{"r":"86","t":"21:33:52","h":"Ouest","s":"25N-H54N000S-80-S"},{"r":"86","t":"21:33:52","h":"Ouest","s":"25N-H54NV10S-82-S"},{"r":"86","t":"21:33:52","h":"Ouest","s":"25N-H54NV20S-80-S"},{"r":"86","t":"21:33:52","h":"Ouest","s":"25S-H54S000S-82-S"},{"r":"86","t":"21:46:52","h":"Ouest","s":"25N-H54N000A-80-A"},{"r":"86","t":"21:46:52","h":"Ouest","s":"25N-H54NV10A-80-A"},{"r":"86","t":"21:46:52","h":"Ouest","s":"25N-H54NV20A-80-A"},{"r":"86","t":"21:46:52","h":"Ouest","s":"25S-H54S000A-83-A"},{"r":"86","t":"21:57:52","h":"Ouest","s":"25N-H54N000I-80-I"},{"r":"86","t":"21:57:52","h":"Ouest","s":"25N-H54N100F-80-F1"},{"r":"86","t":"21:57:52","h":"Ouest","s":"25N-H54N200F-80-F2"},{"r":"86","t":"21:57:52","h":"Ouest","s":"25N-H54N300F-80-F3"},{"r":"86","t":"21:57:52","h":"Ouest","s":"25N-H54N400F-80-F4"},{"r":"86","t":"21:57:52","h":"Ouest","s":"25N-H54NV10I-80-I"},{"r":"86","t":"21:57:52","h":"Ouest","s":"25N-H54NV20I-80-I"},{"r":"86","t":"21:57:52","h":"Ouest","s":"25S-H54S000I-82-I"},{"r":"86","t":"21:57:52","h":"Ouest","s":"25S-H54S100F-80-F1"},{"r":"86","t":"21:57:52","h":"Ouest","s":"25S-H54S200F-80-F2"},{"r":"86","t":"22:02:52","h":"Ouest","s":"25N-H54N000S-80-S"},{"r":"86","t":"22:02:52","h":"Ouest","s":"25N-H54NV10S-82-S"},{"r":"86","t":"22:02:52","h":"Ouest","s":"25N-H54NV20S-80-S"},{"r":"86","t":"22:02:52","h":"Ouest","s":"25S-H54S000S-82-S"},{"r":"86","t":"22:18:52","h":"Ouest","s":"25N-H54N000A-80-A"},{"r":"86","t":"22:18:52","h":"Ouest","s":"25N-H54NV10A-80-A"},{"r":"86","t":"22:18:52","h":"Ouest","s":"25N-H54NV20A-80-A"},{"r":"86","t":"22:18:52","h":"Ouest","s":"25S-H54S000A-83-A"},{"r":"86","t":"22:28:52","h":"Ouest","s":"25N-H54N000I-80-I"},{"r":"86","t":"22:28:52","h":"Ouest","s":"25N-H54N100F-80-F1"},{"r":"86","t":"22:28:52","h":"Ouest","s":"25N-H54N200F-80-F2"},{"r":"86","t":"22:28:52","h":"Ouest","s":"25N-H54N300F-80-F3"},{"r":"86","t":"22:28:52","h":"Ouest","s":"25N-H54N400F-80-F4"},{"r":"86","t":"22:28:52","h":"Ouest","s":"25N-H54NV10I-80-I"},{"r":"86","t":"22:28:52","h":"Ouest","s":"25N-H54NV20I-80-I"},{"r":"86","t":"22:28:52","h":"Ouest","s":"25S-H54S000I-82-I"},{"r":"86","t":"22:28:52","h":"Ouest","s":"25S-H54S100F-80-F1"},{"r":"86","t":"22:28:52","h":"Ouest","s":"25S-H54S200F-80-F2"},{"r":"86","t":"22:31:52","h":"Ouest","s":"25N-H54N000S-80-S"},{"r":"86","t":"22:31:52","h":"Ouest","s":"25N-H54NV10S-82-S"},{"r":"86","t":"22:31:52","h":"Ouest","s":"25N-H54NV20S-80-S"},{"r":"86","t":"22:31:52","h":"Ouest","s":"25S-H54S000S-82-S"},{"r":"86","t":"22:48:52","h":"Ouest","s":"25N-H54N000A-80-A"},{"r":"86","t":"22:48:52","h":"Ouest","s":"25N-H54NV10A-80-A"},{"r":"86","t":"22:48:52","h":"Ouest","s":"25N-H54NV20A-80-A"},{"r":"86","t":"22:48:52","h":"Ouest","s":"25S-H54S000A-83-A"},{"r":"86","t":"22:58:52","h":"Ouest","s":"25N-H54N000S-80-S"},{"r":"86","t":"22:58:52","h":"Ouest","s":"25N-H54NV10S-82-S"},{"r":"86","t":"22:58:52","h":"Ouest","s":"25N-H54NV20S-80-S"},{"r":"86","t":"22:58:52","h":"Ouest","s":"25S-H54S000S-82-S"},{"r":"86","t":"22:59:52","h":"Ouest","s":"25N-H54N000I-80-I"},{"r":"86","t":"22:59:52","h":"Ouest","s":"25N-H54N100F-80-F1"},{"r":"86","t":"22:59:52","h":"Ouest","s":"25N-H54N200F-80-F2"},{"r":"86","t":"22:59:52","h":"Ouest","s":"25N-H54N300F-80-F3"},{"r":"86","t":"22:59:52","h":"Ouest","s":"25N-H54N400F-80-F4"},{"r":"86","t":"22:59:52","h":"Ouest","s":"25N-H54NV10I-80-I"},{"r":"86","t":"22:59:52","h":"Ouest","s":"25N-H54NV20I-80-I"},{"r":"86","t":"22:59:52","h":"Ouest","s":"25S-H54S000I-82-I"},{"r":"86","t":"22:59:52","h":"Ouest","s":"25S-H54S100F-80-F1"},{"r":"86","t":"22:59:52","h":"Ouest","s":"25S-H54S200F-80-F2"},{"r":"86","t":"23:18:52","h":"Ouest","s":"25N-H54N000A-80-A"},{"r":"86","t":"23:18:52","h":"Ouest","s":"25N-H54NV10A-80-A"},{"r":"86","t":"23:18:52","h":"Ouest","s":"25N-H54NV20A-80-A"},{"r":"86","t":"23:18:52","h":"Ouest","s":"25S-H54S000A-83-A"},{"r":"86","t":"23:24:52","h":"Ouest","s":"25N-H54N000S-80-S"},{"r":"86","t":"23:24:52","h":"Ouest","s":"25N-H54NV10S-82-S"},{"r":"86","t":"23:24:52","h":"Ouest","s":"25N-H54NV20S-80-S"},{"r":"86","t":"23:24:52","h":"Ouest","s":"25S-H54S000S-82-S"},{"r":"86","t":"23:29:52","h":"Ouest","s":"25N-H54N000I-80-I"},{"r":"86","t":"23:29:52","h":"Ouest","s":"25N-H54N100F-80-F1"},{"r":"86","t":"23:29:52","h":"Ouest","s":"25N-H54N200F-80-F2"},{"r":"86","t":"23:29:52","h":"Ouest","s":"25N-H54N300F-80-F3"},{"r":"86","t":"23:29:52","h":"Ouest","s":"25N-H54N400F-80-F4"},{"r":"86","t":"23:29:52","h":"Ouest","s":"25N-H54NV10I-80-I"},{"r":"86","t":"23:29:52","h":"Ouest","s":"25N-H54NV20I-80-I"},{"r":"86","t":"23:29:52","h":"Ouest","s":"25S-H54S000I-82-I"},{"r":"86","t":"23:29:52","h":"Ouest","s":"25S-H54S100F-80-F1"},{"r":"86","t":"23:29:52","h":"Ouest","s":"25S-H54S200F-80-F2"},{"r":"86","t":"23:48:52","h":"Ouest","s":"25N-H54N000A-80-A"},{"r":"86","t":"23:48:52","h":"Ouest","s":"25N-H54NV10A-80-A"},{"r":"86","t":"23:48:52","h":"Ouest","s":"25N-H54NV20A-80-A"},{"r":"86","t":"23:48:52","h":"Ouest","s":"25S-H54S000A-83-A"},{"r":"86","t":"23:53:52","h":"Ouest","s":"25N-H54N000S-80-S"},{"r":"86","t":"23:53:52","h":"Ouest","s":"25N-H54NV10S-82-S"},{"r":"86","t":"23:53:52","h":"Ouest","s":"25N-H54NV20S-80-S"},{"r":"86","t":"23:53:52","h":"Ouest","s":"25S-H54S000S-82-S"},{"r":"86","t":"23:55:52","h":"Ouest","s":"25N-H54N000I-80-I"},{"r":"86","t":"23:55:52","h":"Ouest","s":"25N-H54N100F-80-F1"},{"r":"86","t":"23:55:52","h":"Ouest","s":"25N-H54N200F-80-F2"},{"r":"86","t":"23:55:52","h":"Ouest","s":"25N-H54N300F-80-F3"},{"r":"86","t":"23:55:52","h":"Ouest","s":"25N-H54N400F-80-F4"},{"r":"86","t":"23:55:52","h":"Ouest","s":"25N-H54NV10I-80-I"},{"r":"86","t":"23:55:52","h":"Ouest","s":"25N-H54NV20I-80-I"},{"r":"86","t":"23:55:52","h":"Ouest","s":"25S-H54S000I-82-I"},{"r":"86","t":"23:55:52","h":"Ouest","s":"25S-H54S100F-80-F1"},{"r":"86","t":"23:55:52","h":"Ouest","s":"25S-H54S200F-80-F2"},{"r":"86","t":"24:18:52","h":"Ouest","s":"25N-H54N000A-80-A"},{"r":"86","t":"24:18:52","h":"Ouest","s":"25N-H54NV10A-80-A"},{"r":"86","t":"24:18:52","h":"Ouest","s":"25N-H54NV20A-80-A"},{"r":"86","t":"24:18:52","h":"Ouest","s":"25S-H54S000A-83-A"},{"r":"86","t":"24:23:52","h":"Ouest","s":"25N-H54N000S-80-S"},{"r":"86","t":"24:23:52","h":"Ouest","s":"25N-H54NV10S-82-S"},{"r":"86","t":"24:23:52","h":"Ouest","s":"25N-H54NV20S-80-S"},{"r":"86","t":"24:23:52","h":"Ouest","s":"25S-H54S000S-82-S"},{"r":"86","t":"24:24:52","h":"Ouest","s":"25N-H54N000I-80-I"},{"r":"86","t":"24:24:52","h":"Ouest","s":"25N-H54N100F-80-F1"},{"r":"86","t":"24:24:52","h":"Ouest","s":"25N-H54N200F-80-F2"},{"r":"86","t":"24:24:52","h":"Ouest","s":"25N-H54N300F-80-F3"},{"r":"86","t":"24:24:52","h":"Ouest","s":"25N-H54N400F-80-F4"},{"r":"86","t":"24:24:52","h":"Ouest","s":"25N-H54NV10I-80-I"},{"r":"86","t":"24:24:52","h":"Ouest","s":"25N-H54NV20I-80-I"},{"r":"86","t":"24:24:52","h":"Ouest","s":"25S-H54S000I-82-I"},{"r":"86","t":"24:24:52","h":"Ouest","s":"25S-H54S100F-80-F1"},{"r":"86","t":"24:24:52","h":"Ouest","s":"25S-H54S200F-80-F2"},{"r":"86","t":"24:48:52","h":"Ouest","s":"25N-H54N000A-80-A"},{"r":"86","t":"24:48:52","h":"Ouest","s":"25N-H54NV10A-80-A"},{"r":"86","t":"24:48:52","h":"Ouest","s":"25N-H54NV20A-80-A"},{"r":"86","t":"24:48:52","h":"Ouest","s":"25S-H54S000A-83-A"},{"r":"86","t":"24:52:52","h":"Ouest","s":"25N-H54N000S-80-S"},{"r":"86","t":"24:52:52","h":"Ouest","s":"25N-H54NV10S-82-S"},{"r":"86","t":"24:52:52","h":"Ouest","s":"25N-H54NV20S-80-S"},{"r":"86","t":"24:52:52","h":"Ouest","s":"25S-H54S000S-82-S"},{"r":"86","t":"24:54:52","h":"Ouest","s":"25N-H54N000I-80-I"},{"r":"86","t":"24:54:52","h":"Ouest","s":"25N-H54N100F-80-F1"},{"r":"86","t":"24:54:52","h":"Ouest","s":"25N-H54N200F-80-F2"},{"r":"86","t":"24:54:52","h":"Ouest","s":"25N-H54N300F-80-F3"},{"r":"86","t":"24:54:52","h":"Ouest","s":"25N-H54N400F-80-F4"},{"r":"86","t":"24:54:52","h":"Ouest","s":"25N-H54NV10I-80-I"},{"r":"86","t":"24:54:52","h":"Ouest","s":"25N-H54NV20I-80-I"},{"r":"86","t":"24:54:52","h":"Ouest","s":"25S-H54S000I-82-I"},{"r":"86","t":"24:54:52","h":"Ouest","s":"25S-H54S100F-80-F1"},{"r":"86","t":"24:54:52","h":"Ouest","s":"25S-H54S200F-80-F2"},{"r":"86","t":"25:18:52","h":"Ouest","s":"25N-H54N000A-80-A"},{"r":"86","t":"25:18:52","h":"Ouest","s":"25N-H54NV10A-80-A"},{"r":"86","t":"25:18:52","h":"Ouest","s":"25N-H54NV20A-80-A"},{"r":"86","t":"25:18:52","h":"Ouest","s":"25S-H54S000A-83-A"},{"r":"86","t":"25:22:52","h":"Ouest","s":"25N-H54N000S-80-S"},{"r":"86","t":"25:22:52","h":"Ouest","s":"25N-H54NV10S-82-S"},{"r":"86","t":"25:22:52","h":"Ouest","s":"25N-H54NV20S-80-S"},{"r":"86","t":"25:22:52","h":"Ouest","s":"25S-H54S000S-82-S"},{"r":"86","t":"25:24:52","h":"Ouest","s":"25N-H54N000I-80-I"},{"r":"86","t":"25:24:52","h":"Ouest","s":"25N-H54N100F-80-F1"},{"r":"86","t":"25:24:52","h":"Ouest","s":"25N-H54N200F-80-F2"},{"r":"86","t":"25:24:52","h":"Ouest","s":"25N-H54N300F-80-F3"},{"r":"86","t":"25:24:52","h":"Ouest","s":"25N-H54N400F-80-F4"},{"r":"86","t":"25:24:52","h":"Ouest","s":"25N-H54NV10I-80-I"},{"r":"86","t":"25:24:52","h":"Ouest","s":"25N-H54NV20I-80-I"},{"r":"86","t":"25:24:52","h":"Ouest","s":"25S-H54S000I-82-I"},{"r":"86","t":"25:24:52","h":"Ouest","s":"25S-H54S100F-80-F1"},{"r":"86","t":"25:24:52","h":"Ouest","s":"25S-H54S200F-80-F2"},{"r":"86","t":"25:48:52","h":"Ouest","s":"25N-H54N000A-80-A"},{"r":"86","t":"25:48:52","h":"Ouest","s":"25N-H54NV10A-80-A"},{"r":"86","t":"25:48:52","h":"Ouest","s":"25N-H54NV20A-80-A"},{"r":"86","t":"25:48:52","h":"Ouest","s":"25S-H54S000A-83-A"},{"r":"86","t":"25:52:52","h":"Ouest","s":"25N-H54N000S-80-S"},{"r":"86","t":"25:52:52","h":"Ouest","s":"25N-H54NV10S-82-S"},{"r":"86","t":"25:52:52","h":"Ouest","s":"25N-H54NV20S-80-S"},{"r":"86","t":"25:52:52","h":"Ouest","s":"25S-H54S000S-82-S"},{"r":"86","t":"25:56:52","h":"Ouest","s":"25N-H54N000I-80-I"},{"r":"86","t":"25:56:52","h":"Ouest","s":"25N-H54N100F-80-F1"},{"r":"86","t":"25:56:52","h":"Ouest","s":"25N-H54N200F-80-F2"},{"r":"86","t":"25:56:52","h":"Ouest","s":"25N-H54N300F-80-F3"},{"r":"86","t":"25:56:52","h":"Ouest","s":"25N-H54N400F-80-F4"},{"r":"86","t":"25:56:52","h":"Ouest","s":"25N-H54NV10I-80-I"},{"r":"86","t":"25:56:52","h":"Ouest","s":"25N-H54NV20I-80-I"},{"r":"86","t":"25:56:52","h":"Ouest","s":"25S-H54S000I-82-I"},{"r":"86","t":"25:56:52","h":"Ouest","s":"25S-H54S100F-80-F1"},{"r":"86","t":"25:56:52","h":"Ouest","s":"25S-H54S200F-80-F2"},{"r":"86","t":"26:20:52","h":"Ouest","s":"25N-H54N000A-80-A"},{"r":"86","t":"26:20:52","h":"Ouest","s":"25N-H54NV10A-80-A"},{"r":"86","t":"26:20:52","h":"Ouest","s":"25N-H54NV20A-80-A"},{"r":"86","t":"26:20:52","h":"Ouest","s":"25S-H54S000A-83-A"}]